anoapycore/__data.py
anoapycore/__init__.py
anoapycore/column.py
anoapycore/data.py
anoapycore/load.py
anoapycore/py_column.py
anoapycore/py_data.py
anoapycore/py_load.py
anoapycore/py_row.py
anoapycore/py_value.py
anoapycore/row.py
anoapycore/value.py
anoapycore/__eval/__init__.py
anoapycore/chart/__init__.py
anoapycore/chart/boxplot/__init__.py
anoapycore/chart/correlation/__init__.py
anoapycore/chart/cumulative_gain/__init__.py
anoapycore/chart/density/__init__.py
anoapycore/chart/histogram/__init__.py
anoapycore/chart/lift/__init__.py
anoapycore/chart/pairplot/__init__.py
anoapycore/chart/precision_recall/__init__.py
anoapycore/chart/roc/__init__.py
anoapycore/chart/scatterplot/__init__.py
anoapycore/data/__init__.py
anoapycore/data/column.py
anoapycore/data/data.py
anoapycore/data/load.py
anoapycore/data/row.py
anoapycore/data/stat.py
anoapycore/data/value.py
anoapycore/data/column/__init__.py
anoapycore/data/column/column.py
anoapycore/data/column/value.py
anoapycore/data/column/value/__init__.py
anoapycore/data/column/value/null.py
anoapycore/data/column/value/null/__init__.py
anoapycore/data/load/__init__.py
anoapycore/data/load/load.py
anoapycore/data/null/__init__.py
anoapycore/data/row/__index.py
anoapycore/data/row/__init__.py
anoapycore/data/row/__value.py
anoapycore/data/save/__init__.py
anoapycore/data/series/__init__.py
anoapycore/data/stat/__init__.py
anoapycore/data/value/__init__.py
anoapycore/ml/__init__.py
anoapycore/ml/data.py
anoapycore/ml/train.py
anoapycore/ml/association/__init__.py
anoapycore/ml/association/apriori/__init__.py
anoapycore/ml/classification/__init__.py
anoapycore/ml/classification/logistic_regression/__init__.py
anoapycore/ml/classification/logreg/__init__.py
anoapycore/ml/classification/logreg_cv/__init__.py
anoapycore/ml/classification/support_vector_classifier/__init__.py
anoapycore/ml/classification/svc/__init__.py
anoapycore/ml/clustering/__init__.py
anoapycore/ml/clustering/kmeans/__init__.py
anoapycore-0.1.31.dist-info/LICENSE.txt
anoapycore-0.1.31.dist-info/METADATA
anoapycore-0.1.31.dist-info/WHEEL
anoapycore-0.1.31.dist-info/top_level.txt
anoapycore-0.1.31.dist-info/RECORD
